{
    "tabContentLst": [
        {
            "img": "//dimg08.c-ctrip.com/images/fd/tg/g1/M06/CA/CE/CghzflWw392Aeqq0ABjXMP41wIk420_C_221_166.jpg",
            "prdNme": "泰国",
            "price": {
                "amt": 2299.0
            },
            "prdLnk": "//vacations.ctrip.com/list/whole/d-thailand-100021.html?salecity=2",
            "sales": 0,
            "total": 1786,
            "sort": 1,
            "sight": "大峡谷、翡翠湾、大佛寺、斯米兰群岛、金三角、珊瑚岛、芭提雅海滩、竹筏漂流、红岛、白庙",
            "food": "泰式炒面、泰式椰汁鸡汤、椒盐濑尿虾、泰北烤鱼、咖喱蟹、绿咖喱椰汁鸡、马散麻咖喱鸡、泰南咖喱鱼、烤椰塔、泰式咖喱炒蟹、柠檬蒸鲈鱼、咖喱鸡面、泰式炒饭、青木瓜色拉、泰式炒河粉、椰汁鸡汤、海鲜烧烤、菠萝炒饭、青木瓜沙拉、咖喱螃蟹、泰式菠萝炒饭、水果飞饼、椰子冰淇淋、泰式炒稞条、炸椰子丸和枣椰丸、绿咖喱鸡、泰式咖喱蟹、泰式汤米粉、泰式酸辣汤、海鲜、芒果糯米饭、咖啡、泰式青木瓜沙拉、炸猪皮、甲米烤鸡腿、冬阴功汤、青木瓜沙律、龙虾、泰式空心菜"
        },
        {
            "img": "//dimg03.c-ctrip.com/images/fd/tg/g1/M02/79/29/CghzfVWwp1SAD5gHACTpIEDO0sk435_C_221_166.jpg",
            "prdNme": "巴厘岛",
            "price": {
                "amt": 2660.0
            },
            "prdLnk": "//vacations.ctrip.com/list/whole/d-bali-438.html?salecity=2",
            "sales": 0,
            "total": 680,
            "sort": 2,
            "sight": "海龟岛、巴厘岛宝格丽度假村、天空之门、金巴兰海滩、佩妮达岛、水神庙、艾吉、库塔冲浪、巴厘野生动物园、水晶湾",
            "food": "脏鸭餐、烤猪饭、什锦饭、海鲜、印尼炒饭、沙爹、芭蕉叶熏鸭"
        },
        {
            "img": "//dimg02.c-ctrip.com/images/fd/tg/g4/M05/B2/24/CggYHFZ4wWiAKCnuADUUoCnU8w4935_C_221_166.jpg",
            "prdNme": "新加坡",
            "price": {
                "amt": 2685.0
            },
            "prdLnk": "//vacations.ctrip.com/list/whole/d-singapore-21396.html?salecity=2",
            "sales": 0,
            "total": 929,
            "sort": 3,
            "sight": "滨海湾金沙酒店无边泳池、芽笼士乃、滨海湾、夜间野生动物园、新加坡动物园、滨海湾金沙、福康宁公园、时光之翼、加东娘惹文化区、新加坡缆车",
            "food": "叻沙、海南鸡饭、咖喱鱼头、炒粿条、辣椒螃蟹、肉骨茶、沙爹、咖椰吐司"
        },
        {
            "img": "//dimg01.c-ctrip.com/images/100m1f000001gzn8h9DEE_C_221_166.jpg",
            "prdNme": "普吉岛",
            "price": {
                "amt": 6308.0
            },
            "prdLnk": "//vacations.ctrip.com/list/whole/d-phuket-364.html?salecity=2",
            "sales": 0,
            "total": 553,
            "sort": 4,
            "sight": "珊瑚岛、芭东海滩、攀牙湾国家公园、蜜月岛、西蒙人妖秀、普吉岛悦榕庄水疗中心、猴山、迈考海滩假日酒店茶树水疗、皇帝岛、007岛",
            "food": "泰式椰汁鸡汤、椒盐濑尿虾、泰式菠萝炒饭、泰式炒河粉、绿咖喱鸡、冬阴功汤、咖喱蟹、泰式汤米粉、青木瓜沙拉、泰式空心菜"
        },
        {
            "img": "//dimg05.c-ctrip.com/images/100h1f000001grtyg835C_C_221_166.jpg",
            "prdNme": "越南",
            "price": {
                "amt": 2179.0
            },
            "prdLnk": "//vacations.ctrip.com/list/whole/d-vietnam-100046.html?salecity=2",
            "sales": 0,
            "total": 489,
            "sort": 5,
            "sight": "猴岛、珍珠岛、芽庄珍珠岛游乐园、巴拿山、佛手桥、芽庄100蛋矿泥浴、芽庄海滩、下龙湾乘船体验、吉婆岛、美奈海滩",
            "food": "滴漏咖啡、古法烤鱼、越式春卷、甘蔗虾、越式螃蟹、水果奶昔、烤龙虾、越南河粉、海鲜"
        },
        {
            "img": "//dimg03.c-ctrip.com/images/100s0y000000mc3qf0838_C_221_166.jpg",
            "prdNme": "芽庄",
            "price": {
                "amt": 2179.0
            },
            "prdLnk": "//vacations.ctrip.com/list/whole/d-nhatrang-670.html?salecity=2",
            "sales": 0,
            "total": 230,
            "sort": 6,
            "sight": "猴岛、珍珠岛、芽庄珍珠岛游乐园、芽庄100蛋矿泥浴、芽庄海滩、芽庄四岛游、耶尔辛博物馆、叠山岛、I-Resort热矿泥浴、芽庄木偶戏剧院",
            "food": "滴漏咖啡、越式春卷、烤龙虾、越南河粉、海鲜"
        },
        {
            "img": "//dimg01.c-ctrip.com/images/100u0y000000lzko9F7A8_C_221_166.jpg",
            "prdNme": "长滩岛",
            "price": {
                "amt": 4705.0
            },
            "prdLnk": "//vacations.ctrip.com/list/whole/d-boracay-610.html?salecity=2",
            "sales": 0,
            "total": 161,
            "sort": 8,
            "sight": "鳄鱼岛、白沙滩、黄色潜水艇体验、梦想大地艺术博物馆、星期五海滩、灵莉甘海滩、Hacienda Maria庄园、长滩岛飞鱼体验、爱之艇MAHAL私人游艇体验、长滩岛落日风帆体验",
            "food": "Halo-halo、龙虾煲粥、芒果沙冰、牛骨汤、披萨、烤鸡、海鲜拼盘"
        },
        {
            "img": "//dimg02.c-ctrip.com/images/tg/066/221/475/3335939f2fdf4650ab6998ba001e0106_C_221_166.jpg",
            "prdNme": "马来西亚",
            "price": {
                "amt": 3627.0
            },
            "prdLnk": "//vacations.ctrip.com/list/whole/d-malaysia-100022.html?salecity=2",
            "sales": 0,
            "total": 1011,
            "sort": 9,
            "sight": "亚庇、普陀寺、槟城、温泉村、卡帕莱岛、西巴丹岛、双子塔、增江、邦邦岛、娘惹博物馆",
            "food": "叻沙、白咖啡、螃蟹、咖喱面、椰浆饭、沙嗲、老虎虾、煎蕊、海鲜、猪肠粉、海南鸡饭、娘惹菜、橘子冰、福建面、炒粿条、肉骨茶、薄饼、牛杂面、沙爹、榴莲冰淇淋"
        },
        {
            "img": "//dimg02.c-ctrip.com/images/tg/384/375/451/3f191f5020b94abba64ec98e16a464de_C_221_166.jpg",
            "prdNme": "柬埔寨",
            "price": {
                "amt": 4655.0
            },
            "prdLnk": "//vacations.ctrip.com/list/whole/d-cambodia-100081.html?salecity=2",
            "sales": 0,
            "total": 708,
            "sort": 10,
            "sight": "吴哥窟、西池、西哈努克、高龙岛、酒吧街、西哈努克港、金边皇宫、西港王宫、吴哥寺、监狱博物馆",
            "food": "酸汤鱼、柬式火锅、米线、柬式春卷、酱汁炒牛肉、Amok"
        },
        {
            "img": "//dimg08.c-ctrip.com/images/100n0j0000009wxztAAA0_C_221_166.jpg",
            "prdNme": "菲律宾",
            "price": {
                "amt": 4609.0
            },
            "prdLnk": "//vacations.ctrip.com/list/whole/d-philippines-100044.html?salecity=2",
            "sales": 0,
            "total": 225,
            "sort": 11,
            "sight": "白沙滩、鳄鱼岛、科隆岛、百胜滩、苏米龙岛、公主港、菲律宾国际会议中心、菲律宾华人博物馆、宿雾博物馆、宏大湾",
            "food": "Halo Halo、芒果、菲式烧烤、猪排配蒜蓉饭、芒果沙冰、披萨、烤鸡、海鲜、便食(Pancit)、海鲜拼盘、Halo-halo、阿道包(Adobo)、菲式八宝冰、龙虾煲粥、大虾、炸鱼、菲式沙拉、烤猪腿(Crispy Pata)、牛骨汤、阿多波、肝酱烤乳猪(Lechon)、烤猪腿"
        },
        {
            "img": "//dimg03.c-ctrip.com/images/100q1f000001grjt5622F_C_221_166.jpg",
            "prdNme": "清迈",
            "price": {
                "amt": 6020.0
            },
            "prdLnk": "//vacations.ctrip.com/list/whole/d-chiangmai-209.html?salecity=2",
            "sales": 0,
            "total": 431,
            "sort": 12,
            "sight": "竹筏漂流、三塔寺、蒙占山、飞翔的长臂猿丛林飞跃、清迈老虎园、清迈古城、清迈丽拉女子监狱按摩 （帕波嘎店）、茵他侬国家公园、双龙寺、班达歪木雕小镇",
            "food": "炸猪皮、泰式菠萝炒饭、咖喱鸡面、泰北烤鱼、青木瓜色拉、泰式炒河粉、冬阴功汤、咖啡、芒果糯米饭"
        },
        {
            "img": "//dimg02.c-ctrip.com/images/100q1f000001grilmCB98_C_221_166.jpg",
            "prdNme": "曼谷",
            "price": {
                "amt": 2299.0
            },
            "prdLnk": "//vacations.ctrip.com/list/whole/d-bangkok-191.html?salecity=2",
            "sales": 0,
            "total": 746,
            "sort": 13,
            "sight": "四面佛、大皇宫、鬼屋宅邸、彩虹云霄拜约克摩天塔、拉差达火车夜市、王权云顶大厦玻璃观景台、班萨姆然钓鱼度假村、曼谷玩偶博物馆、文华东方酒店·东方水疗中心、金东尼人妖秀",
            "food": "柠檬蒸鲈鱼、椰子冰淇淋、泰式炒河粉、冬阴功汤、绿咖喱鸡、咖喱蟹、芒果糯米饭、青木瓜沙拉"
        },
        {
            "img": "//dimg05.c-ctrip.com/images/100j0n000000e3g497155_C_221_166.jpg",
            "prdNme": "苏梅岛",
            "price": {
                "amt": 9987.0
            },
            "prdLnk": "//vacations.ctrip.com/list/whole/d-kohsamui-566.html?salecity=2",
            "sales": 0,
            "total": 308,
            "sort": 14,
            "sight": "泰国苏梅帕岸岛满月夜派对体验、查汶海滩、千手观音庙、丹岛、苏梅蛇园、秘密佛园、查汶大街、Let's Relax水疗馆（苏梅店）、查武恩湖、安通国家海洋公园户外活动",
            "food": "泰式炒面、泰式炒稞条、冬阴功汤、炸椰子丸和枣椰丸、泰式咖喱蟹、椰汁鸡汤、海鲜烧烤、马散麻咖喱鸡、烤椰塔、泰式青木瓜沙拉"
        },
        {
            "img": "//dimg03.c-ctrip.com/images/tg/651/237/055/7ae6ab4560b24e6fb898fea240098e5d_C_221_166.jpg",
            "prdNme": "沙巴",
            "price": {
                "amt": 5117.0
            },
            "prdLnk": "//vacations.ctrip.com/list/whole/d-sabah-538.html?salecity=2",
            "sales": 0,
            "total": 428,
            "sort": 15,
            "sight": "亚庇、普陀寺、卡帕莱岛、西巴丹岛、邦邦岛、马布岛、马达京岛、敦沙卡兰海洋公园、加雅岛、海河湾红树林",
            "food": "海南鸡饭、橘子冰、螃蟹、肉骨茶、牛杂面、老虎虾、沙爹"
        },
        {
            "img": "//dimg05.c-ctrip.com/images/fd/tg/g1/M05/7F/8F/CghzfFWw9MWAX7l6AC3qk9VhL-s419_C_221_166.jpg",
            "prdNme": "尼泊尔",
            "price": {
                "amt": 6961.0
            },
            "prdLnk": "//vacations.ctrip.com/list/whole/d-nepal-100079.html?salecity=2",
            "sales": 0,
            "total": 43,
            "sort": 16,
            "sight": "达希林藏族村、大鼓、蓝毗尼园、费瓦湖、甘杜克、安娜普尔纳大本营线、斯瓦扬布纳寺、尼泊尔国家博物馆、泰米尔区、阿育王柱",
            "food": "尼泊尔奶茶 、 尼瓦风味、Samosa、 Sekuwa、Butter Chapati、Momo"
        },
        {
            "img": "//dimg01.c-ctrip.com/images/10010i00000097uc33264_C_221_166.jpg",
            "prdNme": "缅甸",
            "price": {
                "amt": 611.0
            },
            "prdLnk": "//vacations.ctrip.com/list/whole/d-myanmar-100077.html?salecity=2",
            "sales": 0,
            "total": 41,
            "sort": 17,
            "sight": "缅甸民族村、皇家湖、乌本桥、维桑海滩、仰光中国城、仰光火车站、曼德勒皇宫、水上市场、大湖、马哈昂美寺",
            "food": "鱼汤米线、缅甸大虾"
        },
        {
            "img": "//dimg04.c-ctrip.com/images/10031f000001gs29i5803_C_221_166.jpg",
            "prdNme": "薄荷岛",
            "price": {
                "amt": 4609.0
            },
            "prdLnk": "//vacations.ctrip.com/list/whole/d-boholisland-1166.html?salecity=2",
            "sales": 0,
            "total": 110,
            "sort": 18,
            "sight": "处女岛、巴里卡萨岛、罗博河、阿罗娜海滩、巴卡容教堂、Doljo海滩、巧克力山、桃心木森林、饮血盟约纪念碑、希纳达南岩洞",
            "food": "Halo Halo、菲式八宝冰、菲式烧烤、猪排配蒜蓉饭、菲式沙拉、阿多波"
        },
        {
            "img": "//dimg03.c-ctrip.com/images/fd/tg/g2/M0B/8D/18/Cghzf1Ww-6SAcf7sAAIHC90qxK8849_C_221_166.jpg",
            "prdNme": "老挝",
            "price": {
                "amt": 258.0
            },
            "prdLnk": "//vacations.ctrip.com/list/whole/d-laos-100105.html?salecity=2",
            "sales": 0,
            "total": 36,
            "sort": 19,
            "sight": "苗族夜市、老挝大象保护村、光西瀑布、阿汗寺、琅勃拉邦撒恩寺、达光西熊类保护中心、吉利寺、四千美岛、Living Land农场体验之旅",
            "food": "琅勃拉邦糯米饭、老挝火锅 、捣木瓜 、万象竹筒饭 、琅勃拉邦烤香肠、考顿、万象糯米饭 、老挝烤鱼 、老挝啤酒、老挝咖啡、腊普 、琅勃拉邦沙拉、舂木瓜 "
        },
        {
            "img": "//dimg08.c-ctrip.com/images/fd/tg/g1/M00/79/D0/CghzfFWwp1qAbKLtACn-SA3lnxk428_C_221_166.jpg",
            "prdNme": "印度尼西亚",
            "price": {
                "amt": 2660.0
            },
            "prdLnk": "//vacations.ctrip.com/list/whole/d-indonesia-100045.html?salecity=2",
            "sales": 0,
            "total": 900,
            "sort": 21,
            "sight": "海龟岛、巴厘岛宝格丽度假村、千岛群岛、印尼国家博物馆、天空之门、金巴兰海滩、民丹岛宝藏湾主题乐园、佩妮达岛、水神庙、印度尼西亚风筝博物馆",
            "food": "脏鸭餐、烤猪饭、什锦饭、浓香牛肉格卜、黄姜饭、海鲜、巴东烩牛肉、串烧印尼沙茶、杂拌什锦菜、沙爹串烧、印尼炒饭（Nasi Goreng）、沙爹、印尼炒饭、芭蕉叶熏鸭"
        },
        {
            "img": "//dimg05.c-ctrip.com/images/100g1e000001f5ym26FBF_C_221_166.jpg",
            "prdNme": "岘港",
            "price": {
                "amt": 4415.0
            },
            "prdLnk": "//vacations.ctrip.com/list/whole/d-danang-669.html?salecity=2",
            "sales": 0,
            "total": 115,
            "sort": 22,
            "sight": "巴拿山、佛手桥、龙桥、美溪海滩、占婆岛潜水体验、峴港大聖堂、诺曼高尔夫俱乐部球场、岘港韩江龙船号游船、魅力岘港演出、灵应寺",
            "food": "滴漏咖啡、越式春卷、越南河粉、海鲜"
        },
        {
            "img": "//dimg07.c-ctrip.com/images/100708000000340a7E9A3_C_221_166.jpg",
            "prdNme": "兰卡威",
            "price": {
                "amt": 3577.0
            },
            "prdLnk": "//vacations.ctrip.com/list/whole/d-langkawi-539.html?salecity=2",
            "sales": 0,
            "total": 168,
            "sort": 23,
            "sight": "温泉村、天空之桥、孕妇岛、兰卡威夕阳帆船落日巡航之旅、兰卡威缆车、兰卡威101天堂岛、稻米博物馆、珍南海滩、珍南海滩水上运动、兰卡威海底世界",
            "food": "白咖啡、海鲜、沙爹、榴莲冰淇淋"
        },
        {
            "img": "//dimg02.c-ctrip.com/images/100w0y000000m5xtlBA65_C_221_166.jpg",
            "prdNme": "吉隆坡",
            "price": {
                "amt": 4102.0
            },
            "prdLnk": "//vacations.ctrip.com/list/whole/d-kualalumpur-45.html?salecity=2",
            "sales": 0,
            "total": 337,
            "sort": 24,
            "sight": "双子塔、增江、国家英雄纪念碑、国家剧院、木槿花园、翡翠博物馆、石英山脉、伊斯兰中心、美拉瓦地山古炮台",
            "food": "叻沙、娘惹菜、白咖啡、椰浆饭、沙嗲、肉骨茶"
        },
        {
            "img": "//dimg02.c-ctrip.com/images/10051f000001gstqxA652_C_221_166.jpg",
            "prdNme": "宿务",
            "price": {
                "amt": 4609.0
            },
            "prdLnk": "//vacations.ctrip.com/list/whole/d-cebu-534.html?salecity=2",
            "sales": 0,
            "total": 111,
            "sort": 26,
            "sight": "宿雾博物馆、奥斯洛布鲸鲨观赏点、圣地亚哥亚普祖屋、麦哲伦十字架、妈妈拍丝瓜岛、1730耶稣教会会址、Our Lady of the Immaculate Conception教堂、锡马拉神殿、宿务充气水上乐园、卡尔邦市场",
            "food": "芒果、大虾、炸鱼、烤猪腿"
        },
        {
            "img": "//dimg04.c-ctrip.com/images/10011f000001h39aw66B5_C_221_166.jpg",
            "prdNme": "甲米",
            "price": {
                "amt": 1188.0
            },
            "prdLnk": "//vacations.ctrip.com/list/whole/sc2.html?sv=%e7%94%b2%e7%b1%b3&st=%e7%94%b2%e7%b1%b3",
            "sales": 0,
            "total": 99,
            "sort": 27,
            "sight": "红岛、红岩、甲米温泉瀑布、竹子岛、通赛湾、骆驼峰、天堂湾、蚊子岛、大皮皮岛、兰迪沙滩",
            "food": "泰式炒面、水果飞饼、泰式咖喱蟹、泰式酸辣汤、芒果糯米饭、泰南咖喱鱼、绿咖喱椰汁鸡、泰式咖喱炒蟹、泰式炒饭、甲米烤鸡腿、冬阴功汤、菠萝炒饭、青木瓜沙律、青木瓜沙拉"
        },
        {
            "img": "//dimg06.c-ctrip.com/images/10080500000011nf50FA6_C_221_166.jpg",
            "prdNme": "胡志明市",
            "price": {
                "amt": 2179.0
            },
            "prdLnk": "//vacations.ctrip.com/list/whole/d-hochiminhcity-434.html?salecity=2",
            "sales": 0,
            "total": 121,
            "sort": 29,
            "sight": "西贡夜市、美托、觉林寺、堤岸、中央邮局、阮惠街、金龙水上木偶剧院、范五老街、胡志明市博物馆、古芝地道",
            "food": "滴漏咖啡、越式春卷、甘蔗虾、越式螃蟹、越南河粉"
        }
    ],
    "name": "东南亚",
    "catgId": 999,
    "dptID": 0,
    "exNme": "",
    "exLnk": "",
    "destCitys": [
        {
            "nme": "境内",
            "pinyin": "JingNei"
        },
        {
            "nme": "日本",
            "pinyin": "RiBen"
        },
        {
            "nme": "东南亚",
            "pinyin": "DongNanYa"
        },
        {
            "nme": "欧洲",
            "pinyin": "OuZhou"
        },
        {
            "nme": "美洲",
            "pinyin": "MeiZhou"
        },
        {
            "nme": "澳中东非",
            "pinyin": "AoZhongDongFei"
        }
    ],
    "adLst": [
        {
            "img": "https://dimg04.c-ctrip.com/images/0zg721200087kvi628F06.jpg",
            "url": "https://vacations.ctrip.com/tangram/ODI0Nw==?ctm_ref=vactang_page_8247",
            "alt": "未接入"
        }
    ]
}